physualize/__init__.py
physualize/makeplots.py
physualize/plotutils.py
physualize-0.0.2.data/scripts/physualize
physualize-0.0.2.dist-info/LICENSE
physualize-0.0.2.dist-info/METADATA
physualize-0.0.2.dist-info/WHEEL
physualize-0.0.2.dist-info/top_level.txt
physualize-0.0.2.dist-info/RECORD
