Metadata-Version: 2.1
Name: physualize
Version: 0.0.2
Summary: a small package to visualise the distributions which are common in HEP (and in general) distribution.
Home-page: https://github.com/ExoPie/physualize
Author: Raman Khurana
Author-email: ramankhurana1986@gmail.com
License: UNKNOWN
Platform: UNKNOWN
Classifier: Programming Language :: Python :: 2
Classifier: License :: OSI Approved :: MIT License
Classifier: Operating System :: OS Independent
Requires-Python: >=2.7
